virtbak/__init__.py
virtbak/__main__.py
virtbak/virtbak.py
virtbak/virt/config.py
virtbak/virt/virt.py
virtbak-0.9.dist-info/METADATA
virtbak-0.9.dist-info/WHEEL
virtbak-0.9.dist-info/entry_points.txt
virtbak-0.9.dist-info/top_level.txt
virtbak-0.9.dist-info/RECORD
