Metadata-Version: 2.1
Name: virtbak
Version: 0.9
Summary: Backup virtual machines from LibVirt
Home-page: https://gitlab.com/oytunistrator/virt-backup
Author: Oytun OZDEMIR
Author-email: oytunozdemir@yandex.com
License: UNKNOWN
Platform: UNKNOWN
Classifier: Programming Language :: Python :: 3
Classifier: License :: OSI Approved :: MIT License
Classifier: Operating System :: OS Independent
Requires-Dist: attrs
Requires-Dist: libvirt-python
Requires-Dist: lxml
